[{"__type__":"cc.AnimationClip","_name":"boss_come","_duration":2.0833333333333335,"curveData":{"paths":{"content":{"props":{"active":[{"frame":0,"value":false},{"frame":0.05,"value":true},{"frame":2.0833333333333335,"value":false}],"opacity":[{"frame":0,"value":255},{"frame":0.05,"value":255},{"frame":0.5,"value":100},{"frame":1,"value":255},{"frame":1.5,"value":100},{"frame":2,"value":255}]}},"content/bottom":{"props":{"x":[{"frame":0,"value":0},{"frame":0.05,"value":0},{"frame":2,"value":-590}]}},"content/top":{"props":{"x":[{"frame":0,"value":0},{"frame":0.05,"value":0},{"frame":2,"value":634}]}}}}},[{"__type__":"cc.Prefab","_name":"boss_come_ui","data":{"__id__":1}},{"__type__":"cc.Node","_name":"boss_come_ui","_children":[{"__id__":2}],"_level":1,"_components":[{"__id__":15},{"__type__":"eca5cQDV4hJVpEkQ9p/LWwx","node":{"__id__":1},"curAnimation":{"__id__":15}}],"_prefab":{"__type__":"cc.PrefabInfo","root":{"__id__":1},"asset":{"__id__":0},"fileId":"d8DKtdfz1EL6RHzAd9yKCB"},"_scale":{"__type__":"cc.Vec3","x":1,"y":1,"z":1}},{"__type__":"cc.Node","_name":"content","_parent":{"__id__":1},"_children":[{"__id__":3},{"__id__":4},{"__id__":5},{"__id__":10}],"_active":false,"_level":2,"_prefab":{"__type__":"cc.PrefabInfo","root":{"__id__":1},"asset":{"__id__":0},"fileId":"cdB7IfJdhCpKcc4QaIDogv"},"_scale":{"__type__":"cc.Vec3","x":1,"y":1,"z":1}},{"__type__":"cc.Node","_name":"bg","_parent":{"__id__":2},"_level":3,"_components":[{"__type__":"cc.Sprite","node":{"__id__":3},"_spriteFrame":{"__uuid__":"a2MjXRFdtLlYQ5ouAFv/+R"},"_sizeMode":0}],"_prefab":{"__type__":"cc.PrefabInfo","root":{"__id__":1},"asset":{"__id__":0},"fileId":"fesvMhH8BH9IfRaRV+WvCt"},"_opacity":59,"_color":{"__type__":"cc.Color","r":57,"g":1,"b":1},"_contentSize":{"__type__":"cc.Size","width":1000,"height":1500},"_scale":{"__type__":"cc.Vec3","x":1,"y":1,"z":1}},{"__type__":"cc.Node","_name":"boss_01","_parent":{"__id__":2},"_level":3,"_components":[{"__type__":"cc.Sprite","node":{"__id__":4},"_spriteFrame":{"__uuid__":"94/lP2qP5PPL1LCAVn7k9V"},"_sizeMode":0}],"_prefab":{"__type__":"cc.PrefabInfo","root":{"__id__":1},"asset":{"__id__":0},"fileId":"56Qp4SkflI67fytc04m71r"},"_contentSize":{"__type__":"cc.Size","width":248,"height":252},"_scale":{"__type__":"cc.Vec3","x":1,"y":1,"z":1}},{"__type__":"cc.Node","_name":"bottom","_parent":{"__id__":2},"_children":[{"__id__":6},{"__id__":7},{"__id__":8},{"__id__":9}],"_level":3,"_prefab":{"__type__":"cc.PrefabInfo","root":{"__id__":1},"asset":{"__id__":0},"fileId":"a6Vaa862xLcIPWTPCxqO1q"},"_position":{"__type__":"cc.Vec3","y":-312},"_scale":{"__type__":"cc.Vec3","x":1,"y":1,"z":1}},{"__type__":"cc.Node","_name":"boss_02","_parent":{"__id__":5},"_level":4,"_components":[{"__type__":"cc.Sprite","node":{"__id__":6},"_spriteFrame":{"__uuid__":"f9kSK+OuRJfJrjChKc/+fq"},"_sizeMode":0}],"_prefab":{"__type__":"cc.PrefabInfo","root":{"__id__":1},"asset":{"__id__":0},"fileId":"c4ASJDsglHVK5rmp5bzo8g"},"_contentSize":{"__type__":"cc.Size","width":260,"height":60},"_position":{"__type__":"cc.Vec3","x":-168},"_scale":{"__type__":"cc.Vec3","x":1,"y":1,"z":1}},{"__type__":"cc.Node","_name":"boss_02","_parent":{"__id__":5},"_level":4,"_components":[{"__type__":"cc.Sprite","node":{"__id__":7},"_spriteFrame":{"__uuid__":"f9kSK+OuRJfJrjChKc/+fq"},"_sizeMode":0}],"_prefab":{"__type__":"cc.PrefabInfo","root":{"__id__":1},"asset":{"__id__":0},"fileId":"d5DpDlQjFP5pKHFr6Sfjm0"},"_contentSize":{"__type__":"cc.Size","width":260,"height":60},"_position":{"__type__":"cc.Vec3","x":158},"_scale":{"__type__":"cc.Vec3","x":1,"y":1,"z":1}},{"__type__":"cc.Node","_name":"line","_parent":{"__id__":5},"_level":4,"_components":[{"__type__":"cc.Sprite","node":{"__id__":8},"_spriteFrame":{"__uuid__":"a2MjXRFdtLlYQ5ouAFv/+R"},"_sizeMode":0}],"_prefab":{"__type__":"cc.PrefabInfo","root":{"__id__":1},"asset":{"__id__":0},"fileId":"716Q7Mr0tJfKk79kGycVkt"},"_color":{"__type__":"cc.Color","r":255,"g":67,"b":67},"_contentSize":{"__type__":"cc.Size","width":2000,"height":10},"_position":{"__type__":"cc.Vec3","y":51},"_scale":{"__type__":"cc.Vec3","x":1,"y":1,"z":1}},{"__type__":"cc.Node","_name":"line","_parent":{"__id__":5},"_level":4,"_components":[{"__type__":"cc.Sprite","node":{"__id__":9},"_spriteFrame":{"__uuid__":"a2MjXRFdtLlYQ5ouAFv/+R"},"_sizeMode":0}],"_prefab":{"__type__":"cc.PrefabInfo","root":{"__id__":1},"asset":{"__id__":0},"fileId":"ebj9YlRI1O7ofG6ghh1DAU"},"_color":{"__type__":"cc.Color","r":255,"g":67,"b":67},"_contentSize":{"__type__":"cc.Size","width":2000,"height":10},"_position":{"__type__":"cc.Vec3","y":-49},"_scale":{"__type__":"cc.Vec3","x":1,"y":1,"z":1}},{"__type__":"cc.Node","_name":"top","_parent":{"__id__":2},"_children":[{"__id__":11},{"__id__":12},{"__id__":13},{"__id__":14}],"_level":3,"_prefab":{"__type__":"cc.PrefabInfo","root":{"__id__":1},"asset":{"__id__":0},"fileId":"65ZyaSFEJEW6AIrNiElTel"},"_position":{"__type__":"cc.Vec3","y":350},"_scale":{"__type__":"cc.Vec3","x":1,"y":1,"z":1}},{"__type__":"cc.Node","_name":"boss_02","_parent":{"__id__":10},"_level":4,"_components":[{"__type__":"cc.Sprite","node":{"__id__":11},"_spriteFrame":{"__uuid__":"f9kSK+OuRJfJrjChKc/+fq"},"_sizeMode":0}],"_prefab":{"__type__":"cc.PrefabInfo","root":{"__id__":1},"asset":{"__id__":0},"fileId":"ea0iOZ+B5EdZu/WE7j4ikj"},"_contentSize":{"__type__":"cc.Size","width":260,"height":60},"_position":{"__type__":"cc.Vec3","x":-168},"_scale":{"__type__":"cc.Vec3","x":1,"y":1,"z":1}},{"__type__":"cc.Node","_name":"boss_02","_parent":{"__id__":10},"_level":4,"_components":[{"__type__":"cc.Sprite","node":{"__id__":12},"_spriteFrame":{"__uuid__":"f9kSK+OuRJfJrjChKc/+fq"},"_sizeMode":0}],"_prefab":{"__type__":"cc.PrefabInfo","root":{"__id__":1},"asset":{"__id__":0},"fileId":"8c2DYum99H9qJZlqN5mToV"},"_contentSize":{"__type__":"cc.Size","width":260,"height":60},"_position":{"__type__":"cc.Vec3","x":158},"_scale":{"__type__":"cc.Vec3","x":1,"y":1,"z":1}},{"__type__":"cc.Node","_name":"line","_parent":{"__id__":10},"_level":4,"_components":[{"__type__":"cc.Sprite","node":{"__id__":13},"_spriteFrame":{"__uuid__":"a2MjXRFdtLlYQ5ouAFv/+R"},"_sizeMode":0}],"_prefab":{"__type__":"cc.PrefabInfo","root":{"__id__":1},"asset":{"__id__":0},"fileId":"66lcsn6fRLqbuNW/Fp7C/0"},"_color":{"__type__":"cc.Color","r":255,"g":67,"b":67},"_contentSize":{"__type__":"cc.Size","width":2000,"height":10},"_position":{"__type__":"cc.Vec3","y":51},"_scale":{"__type__":"cc.Vec3","x":1,"y":1,"z":1}},{"__type__":"cc.Node","_name":"line","_parent":{"__id__":10},"_level":4,"_components":[{"__type__":"cc.Sprite","node":{"__id__":14},"_spriteFrame":{"__uuid__":"a2MjXRFdtLlYQ5ouAFv/+R"},"_sizeMode":0}],"_prefab":{"__type__":"cc.PrefabInfo","root":{"__id__":1},"asset":{"__id__":0},"fileId":"38EkHRT79MQJN6YtT8BXRh"},"_color":{"__type__":"cc.Color","r":255,"g":67,"b":67},"_contentSize":{"__type__":"cc.Size","width":2000,"height":10},"_position":{"__type__":"cc.Vec3","y":-49},"_scale":{"__type__":"cc.Vec3","x":1,"y":1,"z":1}},{"__type__":"cc.Animation","node":{"__id__":1},"_defaultClip":{"__uuid__":"89upb/W09E7oVPpmpNZlQM"},"_clips":[{"__uuid__":"89upb/W09E7oVPpmpNZlQM"}]}]]